pyrpg.py
pyrpg-1.31.dist-info/DESCRIPTION.rst
pyrpg-1.31.dist-info/METADATA
pyrpg-1.31.dist-info/RECORD
pyrpg-1.31.dist-info/WHEEL
pyrpg-1.31.dist-info/metadata.json
pyrpg-1.31.dist-info/top_level.txt
