Metadata-Version: 2.0
Name: pyrpg
Version: 1.31
Summary: The PyRPG Lib, Written By Nirudium
Home-page: https://github.com/NoorMkdad/PYRPG1
Author: Nirudium
Author-email: nirudium@riseup.net
License: UNKNOWN
Platform: UNKNOWN
